rkLLM/__init__.py
rkLLM/Hello.py
rkllm-1.1.0.dist-info/METADATA
rkllm-1.1.0.dist-info/WHEEL
rkllm-1.1.0.dist-info/RECORD
